youtube_to_anki/__init__.py
youtube_to_anki/anki.py
youtube_to_anki/main.py
youtube_to_anki/utils.py
youtube_to_anki/youtube/__init__.py
youtube_to_anki/youtube/audio.py
youtube_to_anki/youtube/info.py
youtube_to_anki/youtube/transcript.py
youtube_to_anki-0.1.3.dist-info/entry_points.txt
youtube_to_anki-0.1.3.dist-info/LICENSE
youtube_to_anki-0.1.3.dist-info/WHEEL
youtube_to_anki-0.1.3.dist-info/METADATA
youtube_to_anki-0.1.3.dist-info/RECORD
